avents/__init__.py
avents/event.py
avents/listener.py
avents/type.py
avents-0.8.1.dist-info/LICENSE
avents-0.8.1.dist-info/METADATA
avents-0.8.1.dist-info/WHEEL
avents-0.8.1.dist-info/top_level.txt
avents-0.8.1.dist-info/zip-safe
avents-0.8.1.dist-info/RECORD
