Metadata-Version: 2.1
Name: avents
Version: 0.8.1
Summary: An asynchronous event library
Home-page: https://gitlab.cloud-technology.io/Open-Source/async-events
Author: Price Hiller
Author-email: philler3138@gmail.com
License: BSD 3-Clause
Project-URL: Documentation, https://gitlab.cloud-technology.io/Open-Source/async-events/docs/
Project-URL: Tracker, https://gitlab.cloud-technology.io/Open-Source/async-events/issues/
Platform: UNKNOWN
Classifier: Programming Language :: Python :: 3
Classifier: Operating System :: OS Independent
Requires-Python: >=3.9
